lan_download/__init__.py
lan_download-0.1.29.dist-info/LICENSE
lan_download-0.1.29.dist-info/METADATA
lan_download-0.1.29.dist-info/WHEEL
lan_download-0.1.29.dist-info/top_level.txt
lan_download-0.1.29.dist-info/RECORD
