Metadata-Version: 2.1
Name: lan-download
Version: 0.1.29
Summary: 提供蓝奏云文件批量下载/获取直链功能
Home-page: https://blog.csdn.net/qq_45429426
Author: manyougz
Author-email: 25275789@qq.com
License: UNKNOWN
Platform: UNKNOWN
Classifier: Programming Language :: Python :: 3
Classifier: License :: OSI Approved :: MIT License
License-File: LICENSE
Requires-Dist: requests (>=2.25.0)
Requires-Dist: lxml (>=4.6.1)
